XiangJisuanjiKexuejiaYiyangSikaoCBan/README.md
XiangJisuanjiKexuejiaYiyangSikaoCBan/__init__.py
XiangJisuanjiKexuejiaYiyangSikaoCBan/__main__.py
XiangJisuanjiKexuejiaYiyangSikaoCBan/file.epub
XiangJisuanjiKexuejiaYiyangSikaoCBan/index.html
XiangJisuanjiKexuejiaYiyangSikaoCBan/css/__init__.py
XiangJisuanjiKexuejiaYiyangSikaoCBan/css/annotations.css
XiangJisuanjiKexuejiaYiyangSikaoCBan/css/main.css
XiangJisuanjiKexuejiaYiyangSikaoCBan/css/normalize.css
XiangJisuanjiKexuejiaYiyangSikaoCBan/css/popup.css
XiangJisuanjiKexuejiaYiyangSikaoCBan/font/__init__.py
XiangJisuanjiKexuejiaYiyangSikaoCBan/font/fontello.eot
XiangJisuanjiKexuejiaYiyangSikaoCBan/font/fontello.svg
XiangJisuanjiKexuejiaYiyangSikaoCBan/font/fontello.ttf
XiangJisuanjiKexuejiaYiyangSikaoCBan/font/fontello.woff
XiangJisuanjiKexuejiaYiyangSikaoCBan/img/__init__.py
XiangJisuanjiKexuejiaYiyangSikaoCBan/img/annotator-glyph-sprite.png
XiangJisuanjiKexuejiaYiyangSikaoCBan/img/annotator-icon-sprite.png
XiangJisuanjiKexuejiaYiyangSikaoCBan/img/apple-touch-icon.png
XiangJisuanjiKexuejiaYiyangSikaoCBan/img/cancelfullscreen.png
XiangJisuanjiKexuejiaYiyangSikaoCBan/img/close.png
XiangJisuanjiKexuejiaYiyangSikaoCBan/img/fullscreen.png
XiangJisuanjiKexuejiaYiyangSikaoCBan/img/loader.gif
XiangJisuanjiKexuejiaYiyangSikaoCBan/img/menu-icon.png
XiangJisuanjiKexuejiaYiyangSikaoCBan/img/save.png
XiangJisuanjiKexuejiaYiyangSikaoCBan/img/saved.png
XiangJisuanjiKexuejiaYiyangSikaoCBan/img/settings-s.png
XiangJisuanjiKexuejiaYiyangSikaoCBan/img/settings.png
XiangJisuanjiKexuejiaYiyangSikaoCBan/img/star.png
XiangJisuanjiKexuejiaYiyangSikaoCBan/js/__init__.py
XiangJisuanjiKexuejiaYiyangSikaoCBan/js/epub.js
XiangJisuanjiKexuejiaYiyangSikaoCBan/js/epub.min.js
XiangJisuanjiKexuejiaYiyangSikaoCBan/js/epub.min.map
XiangJisuanjiKexuejiaYiyangSikaoCBan/js/hooks.min.js
XiangJisuanjiKexuejiaYiyangSikaoCBan/js/hooks.min.map
XiangJisuanjiKexuejiaYiyangSikaoCBan/js/reader.js
XiangJisuanjiKexuejiaYiyangSikaoCBan/js/reader.js.map
xiang_jisuanji_kexuejia_yiyang_sikao_c_ban-2024.2.29.0.dist-info/METADATA
xiang_jisuanji_kexuejia_yiyang_sikao_c_ban-2024.2.29.0.dist-info/WHEEL
xiang_jisuanji_kexuejia_yiyang_sikao_c_ban-2024.2.29.0.dist-info/entry_points.txt
xiang_jisuanji_kexuejia_yiyang_sikao_c_ban-2024.2.29.0.dist-info/top_level.txt
xiang_jisuanji_kexuejia_yiyang_sikao_c_ban-2024.2.29.0.dist-info/RECORD
